figure_templates/__init__.py
figure_templates/axes.py
figure_templates/config.py
figure_templates/layouts.py
figure_templates/styles.py
figure_templates/version.py
figure_templates/layouts/print_aside.yml
figure_templates/layouts/print_fullwidth.yml
figure_templates/layouts/print_textwidth.yml
figure_templates/layouts/slide_fullwidth.yml
figure_templates/layouts/slide_square.yml
figure_templates/stylesheets/clean.mplstyle
figure_templates/stylesheets/main.mplstyle
figure_templates/stylesheets/print.mplstyle
figure_templates/stylesheets/print_miniatures.mplstyle
figure_templates/stylesheets/slide.mplstyle
figure_templates/stylesheets/slide_miniatures.mplstyle
mpl_figure_templates-0.1.1.dist-info/METADATA
mpl_figure_templates-0.1.1.dist-info/WHEEL
mpl_figure_templates-0.1.1.dist-info/licenses/LICENSE
mpl_figure_templates-0.1.1.dist-info/RECORD
