Metadata-Version: 2.3
Name: mpl-figure-templates
Version: 0.1.1
Summary: Templates for customizing layouts and styles of Matplotlib figures
Project-URL: Homepage, https://github.com/numerical-io/mpl_figure_templates
License-Expression: MIT
License-File: LICENSE
Requires-Python: <4,>=3.9
Requires-Dist: matplotlib>=2.0.0
Requires-Dist: platformdirs>=2.0.0
Requires-Dist: python-dotenv>0.10.1
Requires-Dist: pyyaml>=3.13
